[
  {
    "video": "IMG_2817.MOV",
    "duration_s": 3.966666666666667,
    "glove_pop_time_s": 1.5977551020408163,
    "glove_pop_amplitude": 12426.238636363636,
    "audio_amplitude": 27344,
    "decay_ratio": 0.023005528127313362,
    "pop_zcr": 70,
    "fb_score": 0.9091346863878861,
    "ball_strike_detected": "Strike",
    "bs_confidence": "medium",
    "bs_score": 3,
    "detected_pitch_type": "Fastball",
    "classification_votes": {
      "Fastball": 7
    },
    "actual_pitch_type": null,
    "actual_result": null,
    "pitch_type_correct": null,
    "video_features": {
      "center_peakPos": 0.8235294117647058,
      "center_lateFlight": 1.5895596498774884,
      "center_flightAvg": 63053.547583818436,
      "center_flightCV": 0.2714055931664203,
      "pitchLane_peakPos": 0.6764705882352942,
      "pitchLane_lateFlight": 1.337933130386076,
      "pitchLane_flightAvg": 55432.269352436066,
      "pitchLane_flightCV": 0.1745824422538398,
      "catchZone_peakPos": 0.9705882352941176,
      "catchZone_lateFlight": 1.370805774461835,
      "catchZone_flightAvg": 5120.931694030762,
      "catchZone_flightCV": 0.5831257098730496,
      "edgeDensityPrePop": 18.611856098838384,
      "edgeDensityAtPop": 18.470463581183527
    }
  },
  {
    "video": "IMG_2818.MOV",
    "duration_s": 11.369319727891156,
    "glove_pop_time_s": 4.120680272108843,
    "glove_pop_amplitude": 12018.71590909091,
    "audio_amplitude": 26576,
    "decay_ratio": 0.005231599859238466,
    "pop_zcr": 39,
    "fb_score": 0.8545820401143777,
    "ball_strike_detected": "Strike",
    "bs_confidence": "high",
    "bs_score": 4,
    "detected_pitch_type": "Fastball",
    "classification_votes": {
      "Fastball": 7
    },
    "actual_pitch_type": null,
    "actual_result": null,
    "pitch_type_correct": null,
    "video_features": {
      "center_peakPos": 0.7058823529411765,
      "center_lateFlight": 1.4478607737402054,
      "center_flightAvg": 34839.717099666595,
      "center_flightCV": 0.24284684788513722,
      "pitchLane_peakPos": 0.6764705882352942,
      "pitchLane_lateFlight": 1.3837629957382012,
      "pitchLane_flightAvg": 32391.049789190292,
      "pitchLane_flightCV": 0.2650417066729176,
      "catchZone_peakPos": 0.9705882352941176,
      "catchZone_lateFlight": 1.4365681003253714,
      "catchZone_flightAvg": 5028.927468061447,
      "catchZone_flightCV": 0.48933137127340415,
      "edgeDensityPrePop": 15.759508602820485,
      "edgeDensityAtPop": 15.885140993764315
    }
  },
  {
    "video": "IMG_2819.MOV",
    "duration_s": 5.588004535147392,
    "glove_pop_time_s": 0.5060997732426303,
    "glove_pop_amplitude": 1437.8863636363637,
    "audio_amplitude": 1860,
    "decay_ratio": 0.258730388948481,
    "pop_zcr": 8,
    "fb_score": 0.18943244292213585,
    "ball_strike_detected": "Strike",
    "bs_confidence": "high",
    "bs_score": 4,
    "detected_pitch_type": "Changeup",
    "classification_votes": {
      "Changeup": 4,
      "Curveball": 2,
      "Fastball": 1
    },
    "actual_pitch_type": null,
    "actual_result": null,
    "pitch_type_correct": null,
    "video_features": {
      "center_peakPos": 0.05263157894736842,
      "center_lateFlight": 0.3141631284420905,
      "center_flightAvg": 62080.93128239314,
      "center_flightCV": 0.5306115457137378,
      "pitchLane_peakPos": 0.21052631578947367,
      "pitchLane_lateFlight": 0.33462637369376186,
      "pitchLane_flightAvg": 50590.21865466436,
      "pitchLane_flightCV": 0.500875132734798,
      "catchZone_peakPos": 0.21052631578947367,
      "catchZone_lateFlight": 0.49299088037093747,
      "catchZone_flightAvg": 25920.451919142404,
      "catchZone_flightCV": 0.38985248412963214,
      "edgeDensityPrePop": 18.7669201463918,
      "edgeDensityAtPop": 18.61720297904518
    }
  },
  {
    "video": "IMG_2820.MOV",
    "duration_s": 5.204013605442177,
    "glove_pop_time_s": 3.735283446712018,
    "glove_pop_amplitude": 4724.261363636364,
    "audio_amplitude": 9419,
    "decay_ratio": 0.19391577984926972,
    "pop_zcr": 37,
    "fb_score": 0.5156524682764752,
    "ball_strike_detected": "Strike",
    "bs_confidence": "medium",
    "bs_score": 2,
    "detected_pitch_type": "Changeup",
    "classification_votes": {
      "Changeup": 3,
      "Curveball": 2,
      "Fastball": 2
    },
    "actual_pitch_type": null,
    "actual_result": null,
    "pitch_type_correct": null,
    "video_features": {
      "center_peakPos": 0.6764705882352942,
      "center_lateFlight": 1.7713656429424258,
      "center_flightAvg": 78989.99184113741,
      "center_flightCV": 0.31615557948093176,
      "pitchLane_peakPos": 0.7058823529411765,
      "pitchLane_lateFlight": 1.7182740842275592,
      "pitchLane_flightAvg": 70222.78292679787,
      "pitchLane_flightCV": 0.29311910138109215,
      "catchZone_peakPos": 0.6176470588235294,
      "catchZone_lateFlight": 1.2960650588361762,
      "catchZone_flightAvg": 11999.679794028401,
      "catchZone_flightCV": 0.36383972426884303,
      "edgeDensityPrePop": 19.35251456642792,
      "edgeDensityAtPop": 19.24509272257709
    }
  },
  {
    "video": "IMG_2821.MOV",
    "duration_s": 7.10265306122449,
    "glove_pop_time_s": 6.4517233560090705,
    "glove_pop_amplitude": 11022.636363636364,
    "audio_amplitude": 19485,
    "decay_ratio": 0.0017692126166681383,
    "pop_zcr": 39,
    "fb_score": 0.8547169811320755,
    "ball_strike_detected": "Ball",
    "bs_confidence": "medium",
    "bs_score": 1,
    "detected_pitch_type": "Fastball",
    "classification_votes": {
      "Fastball": 7
    },
    "actual_pitch_type": null,
    "actual_result": null,
    "pitch_type_correct": null,
    "video_features": {
      "center_peakPos": 0.8857142857142857,
      "center_lateFlight": 0.6736164212614499,
      "center_flightAvg": 390342.0436781496,
      "center_flightCV": 0.3487881582500492,
      "pitchLane_peakPos": 0.8571428571428571,
      "pitchLane_lateFlight": 0.6102155849126114,
      "pitchLane_flightAvg": 365534.107398808,
      "pitchLane_flightCV": 0.3933301158235071,
      "catchZone_peakPos": 0.6285714285714286,
      "catchZone_lateFlight": 0.8466251938304273,
      "catchZone_flightAvg": 169926.6798171997,
      "catchZone_flightCV": 0.4665409914825433,
      "edgeDensityPrePop": 13.586768614434382,
      "edgeDensityAtPop": 6.941637736125109
    }
  },
  {
    "video": "IMG_2822.MOV",
    "duration_s": 7.572018140589569,
    "glove_pop_time_s": 4.336213151927438,
    "glove_pop_amplitude": 8681.613636363636,
    "audio_amplitude": 23016,
    "decay_ratio": 0.022031626659751356,
    "pop_zcr": 66,
    "fb_score": 0.9018032902524618,
    "ball_strike_detected": "Strike",
    "bs_confidence": "high",
    "bs_score": 5,
    "detected_pitch_type": "Fastball",
    "classification_votes": {
      "Fastball": 7
    },
    "actual_pitch_type": null,
    "actual_result": null,
    "pitch_type_correct": null,
    "video_features": {
      "center_peakPos": 0.6571428571428571,
      "center_lateFlight": 1.873528141527488,
      "center_flightAvg": 78643.49889409542,
      "center_flightCV": 0.34302643045415876,
      "pitchLane_peakPos": 0.6571428571428571,
      "pitchLane_lateFlight": 1.8749003129762634,
      "pitchLane_flightAvg": 70275.8575977683,
      "pitchLane_flightCV": 0.34162036464355006,
      "catchZone_peakPos": 0.7714285714285715,
      "catchZone_lateFlight": 3.544790941034351,
      "catchZone_flightAvg": 27848.578812777996,
      "catchZone_flightCV": 0.6415128005872947,
      "edgeDensityPrePop": 19.27270450660826,
      "edgeDensityAtPop": 19.07859393554305
    }
  },
  {
    "video": "IMG_2823.MOV",
    "error": "No glove pop detected"
  },
  {
    "video": "IMG_2825.MOV",
    "duration_s": 7.1453514739229025,
    "glove_pop_time_s": 4.07718820861678,
    "glove_pop_amplitude": 10820.886363636364,
    "audio_amplitude": 24177,
    "decay_ratio": 0.01066599008073096,
    "pop_zcr": 30,
    "fb_score": 0.8363968864890847,
    "ball_strike_detected": "Strike",
    "bs_confidence": "high",
    "bs_score": 9,
    "detected_pitch_type": "Fastball",
    "classification_votes": {
      "Fastball": 7
    },
    "actual_pitch_type": null,
    "actual_result": null,
    "pitch_type_correct": null,
    "video_features": {
      "center_peakPos": 0.6571428571428571,
      "center_lateFlight": 1.6478048966678605,
      "center_flightAvg": 72183.41086918116,
      "center_flightCV": 0.30576468866332496,
      "pitchLane_peakPos": 0.6571428571428571,
      "pitchLane_lateFlight": 1.8135058913455615,
      "pitchLane_flightAvg": 53261.680435180664,
      "pitchLane_flightCV": 0.44191800870522285,
      "catchZone_peakPos": 0.8285714285714286,
      "catchZone_lateFlight": 1.6290095869545385,
      "catchZone_flightAvg": 17395.070742607117,
      "catchZone_flightCV": 0.3278663029555436,
      "edgeDensityPrePop": 21.22994014299232,
      "edgeDensityAtPop": 20.48573230590855
    }
  },
  {
    "video": "IMG_2826.MOV",
    "duration_s": 6.441337868480725,
    "glove_pop_time_s": 1.781768707482993,
    "glove_pop_amplitude": 3208.3977272727275,
    "audio_amplitude": 9156,
    "decay_ratio": 0.07611022388917253,
    "pop_zcr": 67,
    "fb_score": 0.5892787048855097,
    "ball_strike_detected": "Strike",
    "bs_confidence": "high",
    "bs_score": 4,
    "detected_pitch_type": "Changeup",
    "classification_votes": {
      "Changeup": 4,
      "Curveball": 2,
      "Fastball": 1
    },
    "actual_pitch_type": null,
    "actual_result": null,
    "pitch_type_correct": null,
    "video_features": {
      "center_peakPos": 0.22857142857142856,
      "center_lateFlight": 1.8866988754937744,
      "center_flightAvg": 4008.1468980312347,
      "center_flightCV": 0.995342730826895,
      "pitchLane_peakPos": 0.22857142857142856,
      "pitchLane_lateFlight": 1.920245159117998,
      "pitchLane_flightAvg": 3552.615096449852,
      "pitchLane_flightCV": 0.9887785023917989,
      "catchZone_peakPos": 0.22857142857142856,
      "catchZone_lateFlight": 2.796062058074316,
      "catchZone_flightAvg": 1651.9026892781258,
      "catchZone_flightCV": 1.4348810010585598,
      "edgeDensityPrePop": 18.52843963068255,
      "edgeDensityAtPop": 18.552049096439518
    }
  },
  {
    "video": "IMG_2827.MOV",
    "duration_s": 5.886666666666667,
    "glove_pop_time_s": 5.582244897959184,
    "glove_pop_amplitude": 3373.7045454545455,
    "audio_amplitude": 11198,
    "decay_ratio": 0.08009416144226233,
    "pop_zcr": 63,
    "fb_score": 0.6513332763595227,
    "ball_strike_detected": "Ball",
    "bs_confidence": "low",
    "bs_score": 0,
    "detected_pitch_type": "Fastball",
    "classification_votes": {
      "Fastball": 4,
      "Curveball": 2,
      "Changeup": 1
    },
    "actual_pitch_type": null,
    "actual_result": null,
    "pitch_type_correct": null,
    "video_features": {
      "center_peakPos": 0.6571428571428571,
      "center_lateFlight": 1.1271998503462617,
      "center_flightAvg": 118508.49736435711,
      "center_flightCV": 0.2451314336855511,
      "pitchLane_peakPos": 0.6571428571428571,
      "pitchLane_lateFlight": 1.1390630909511528,
      "pitchLane_flightAvg": 70969.01967394352,
      "pitchLane_flightCV": 0.28139195113342824,
      "catchZone_peakPos": 0.6857142857142857,
      "catchZone_lateFlight": 1.2986686738432658,
      "catchZone_flightAvg": 57869.65568162501,
      "catchZone_flightCV": 0.2577782626437868,
      "edgeDensityPrePop": 20.300793387392844,
      "edgeDensityAtPop": 19.945281991400588
    }
  },
  {
    "video": "IMG_2828.MOV",
    "duration_s": 20.649319727891157,
    "glove_pop_time_s": 11.192448979591838,
    "glove_pop_amplitude": 5198.340909090909,
    "audio_amplitude": 12865,
    "decay_ratio": 0.028139288322945922,
    "pop_zcr": 43,
    "fb_score": 0.6826487434082937,
    "ball_strike_detected": "Strike",
    "bs_confidence": "high",
    "bs_score": 9,
    "detected_pitch_type": "Fastball",
    "classification_votes": {
      "Fastball": 6,
      "Curveball": 1
    },
    "actual_pitch_type": null,
    "actual_result": null,
    "pitch_type_correct": null,
    "video_features": {
      "center_peakPos": 0.029411764705882353,
      "center_lateFlight": 0.9926574920217331,
      "center_flightAvg": 156755.68591302633,
      "center_flightCV": 0.06121867985540044,
      "pitchLane_peakPos": 0.029411764705882353,
      "pitchLane_lateFlight": 0.8510408688074861,
      "pitchLane_flightAvg": 171002.1283493638,
      "pitchLane_flightCV": 0.10641280234416366,
      "catchZone_peakPos": 0.5,
      "catchZone_lateFlight": 1.0664570883994593,
      "catchZone_flightAvg": 206067.7540960312,
      "catchZone_flightCV": 0.11607455561932438,
      "edgeDensityPrePop": 15.207114819826629,
      "edgeDensityAtPop": 14.690939660664249
    }
  },
  {
    "video": "IMG_2838.MOV",
    "duration_s": 5.41734693877551,
    "glove_pop_time_s": 3.328095238095238,
    "glove_pop_amplitude": 7389.306818181818,
    "audio_amplitude": 21264,
    "decay_ratio": 0.0025011573584058826,
    "pop_zcr": 63,
    "fb_score": 0.9,
    "ball_strike_detected": "Strike",
    "bs_confidence": "high",
    "bs_score": 6,
    "detected_pitch_type": "Fastball",
    "classification_votes": {
      "Fastball": 7
    },
    "actual_pitch_type": null,
    "actual_result": null,
    "pitch_type_correct": null,
    "video_features": {
      "center_peakPos": 0.8823529411764706,
      "center_lateFlight": 1.373353101150175,
      "center_flightAvg": 100986.19435465336,
      "center_flightCV": 0.21568873700220445,
      "pitchLane_peakPos": 0.8235294117647058,
      "pitchLane_lateFlight": 1.4481835025548384,
      "pitchLane_flightAvg": 84345.87842041254,
      "pitchLane_flightCV": 0.232746018178741,
      "catchZone_peakPos": 0.7941176470588235,
      "catchZone_lateFlight": 1.2962184313159821,
      "catchZone_flightAvg": 36174.52254933119,
      "catchZone_flightCV": 0.32081797423345976,
      "edgeDensityPrePop": 19.169146313732696,
      "edgeDensityAtPop": 19.545559382840125
    }
  },
  {
    "video": "IMG_2839.MOV",
    "duration_s": 5.844013605442177,
    "glove_pop_time_s": 4.523333333333333,
    "glove_pop_amplitude": 2607.3522727272725,
    "audio_amplitude": 3698,
    "decay_ratio": 0.03426845669903209,
    "pop_zcr": 12,
    "fb_score": 0.30637977623929286,
    "ball_strike_detected": "Strike",
    "bs_confidence": "high",
    "bs_score": 5,
    "detected_pitch_type": "Changeup",
    "classification_votes": {
      "Changeup": 4,
      "Curveball": 2,
      "Fastball": 1
    },
    "actual_pitch_type": null,
    "actual_result": null,
    "pitch_type_correct": null,
    "video_features": {
      "center_peakPos": 0.6176470588235294,
      "center_lateFlight": 1.090748588431668,
      "center_flightAvg": 55851.95677006245,
      "center_flightCV": 0.2442737775021943,
      "pitchLane_peakPos": 0.6176470588235294,
      "pitchLane_lateFlight": 1.1183463227593302,
      "pitchLane_flightAvg": 51185.134998202324,
      "pitchLane_flightCV": 0.23552273675793553,
      "catchZone_peakPos": 0.9705882352941176,
      "catchZone_lateFlight": 1.2669085054847584,
      "catchZone_flightAvg": 9419.597758471966,
      "catchZone_flightCV": 0.2801930069947265,
      "edgeDensityPrePop": 18.662654424453056,
      "edgeDensityAtPop": 18.695943299506162
    }
  },
  {
    "video": "IMG_2840.MOV",
    "duration_s": 7.785351473922902,
    "glove_pop_time_s": 4.6925850340136055,
    "glove_pop_amplitude": 7405.113636363636,
    "audio_amplitude": 19407,
    "decay_ratio": 0.03027315188274465,
    "pop_zcr": 39,
    "fb_score": 0.8490339349823558,
    "ball_strike_detected": "Strike",
    "bs_confidence": "medium",
    "bs_score": 2,
    "detected_pitch_type": "Fastball",
    "classification_votes": {
      "Fastball": 7
    },
    "actual_pitch_type": null,
    "actual_result": null,
    "pitch_type_correct": null,
    "video_features": {
      "center_peakPos": 0.5588235294117647,
      "center_lateFlight": 0.9351977447871176,
      "center_flightAvg": 68626.1101217866,
      "center_flightCV": 0.2538523556150901,
      "pitchLane_peakPos": 0.5588235294117647,
      "pitchLane_lateFlight": 0.9372005151211518,
      "pitchLane_flightAvg": 68137.96149355173,
      "pitchLane_flightCV": 0.2583707050384022,
      "catchZone_peakPos": 0.6176470588235294,
      "catchZone_lateFlight": 0.9367871159171272,
      "catchZone_flightAvg": 10654.117554962635,
      "catchZone_flightCV": 0.3323560508119111,
      "edgeDensityPrePop": 18.79636868774492,
      "edgeDensityAtPop": 18.432785279024042
    }
  },
  {
    "video": "IMG_2841.MOV",
    "duration_s": 10.515986394557823,
    "glove_pop_time_s": 3.5771201814058955,
    "glove_pop_amplitude": 9670.363636363636,
    "audio_amplitude": 24743,
    "decay_ratio": 0.01625963647544835,
    "pop_zcr": 78,
    "fb_score": 0.9257236185205543,
    "ball_strike_detected": "Strike",
    "bs_confidence": "high",
    "bs_score": 8,
    "detected_pitch_type": "Fastball",
    "classification_votes": {
      "Fastball": 7
    },
    "actual_pitch_type": null,
    "actual_result": null,
    "pitch_type_correct": null,
    "video_features": {
      "center_peakPos": 0.8285714285714286,
      "center_lateFlight": 2.589608969669081,
      "center_flightAvg": 87568.38222455978,
      "center_flightCV": 0.5379247524254814,
      "pitchLane_peakPos": 0.8285714285714286,
      "pitchLane_lateFlight": 2.9052412503795284,
      "pitchLane_flightAvg": 79834.17758619785,
      "pitchLane_flightCV": 0.5878400044244938,
      "catchZone_peakPos": 0.8,
      "catchZone_lateFlight": 3.363764265426508,
      "catchZone_flightAvg": 31347.408818364143,
      "catchZone_flightCV": 0.6802416466658943,
      "edgeDensityPrePop": 19.825631371587384,
      "edgeDensityAtPop": 19.728506674567623
    }
  },
  {
    "video": "IMG_2842.MOV",
    "duration_s": 48.34,
    "glove_pop_time_s": 3.10437641723356,
    "glove_pop_amplitude": 10006.75,
    "audio_amplitude": 27811,
    "decay_ratio": 0.023084296905557838,
    "pop_zcr": 118,
    "fb_score": 0.9959096875256872,
    "ball_strike_detected": "Strike",
    "bs_confidence": "high",
    "bs_score": 9,
    "detected_pitch_type": "Fastball",
    "classification_votes": {
      "Fastball": 7
    },
    "actual_pitch_type": null,
    "actual_result": null,
    "pitch_type_correct": null,
    "video_features": {
      "center_peakPos": 0.8285714285714286,
      "center_lateFlight": 1.688193184740034,
      "center_flightAvg": 71355.46171104908,
      "center_flightCV": 0.2904785786867032,
      "pitchLane_peakPos": 0.8571428571428571,
      "pitchLane_lateFlight": 1.640273889766546,
      "pitchLane_flightAvg": 59867.77098309994,
      "pitchLane_flightCV": 0.2765003969970198,
      "catchZone_peakPos": 0.9714285714285714,
      "catchZone_lateFlight": 3.80126154668527,
      "catchZone_flightAvg": 25673.454662561417,
      "catchZone_flightCV": 0.7610425239266614,
      "edgeDensityPrePop": 16.166833397649658,
      "edgeDensityAtPop": 15.461406968359398
    }
  }
]